githeat/__init__.py
githeat/__main__.py
githeat/__version__.py
githeat/githeat.py
githeat/interactive.py
githeat/core/__init__.py
githeat/core/_config.py
githeat/core/_logger.py
githeat/util/__init__.py
githeat/util/helpers.py
githeat/util/interactive_navigation.py
githeat-0.2.0.dist-info/LICENSE
githeat-0.2.0.dist-info/METADATA
githeat-0.2.0.dist-info/WHEEL
githeat-0.2.0.dist-info/entry_points.txt
githeat-0.2.0.dist-info/top_level.txt
githeat-0.2.0.dist-info/RECORD
